pg_cham_web/__init__.py
pg_chameleon_web-0.1.dev0.data/scripts/pgcw
pg_chameleon_web-0.1.dev0.data/scripts/pgcw.py
pg_chameleon_web-0.1.dev0.dist-info/LICENSE.txt
pg_chameleon_web-0.1.dev0.dist-info/METADATA
pg_chameleon_web-0.1.dev0.dist-info/WHEEL
pg_chameleon_web-0.1.dev0.dist-info/top_level.txt
pg_chameleon_web-0.1.dev0.dist-info/RECORD
