Metadata-Version: 2.1
Name: pg-chameleon-web
Version: 0.1.dev0
Summary: Web interface for pg_chameleon
Home-page: https://gitlab.com/the4thdoctor/pg_chameleon_web
Author: Federico Campoli
Author-email: the4thdoctor.gallifrey@gmail.com
Maintainer: Federico Campoli
Maintainer-email: the4thdoctor.gallifrey@gmail.com
License: BSD License
Keywords: postgresql replica migration flask web
Platform: linux
Classifier: License :: OSI Approved :: BSD License
Classifier: Environment :: Console
Classifier: Intended Audience :: Developers
Classifier: Intended Audience :: Information Technology
Classifier: Intended Audience :: System Administrators
Classifier: Natural Language :: English
Classifier: Operating System :: POSIX :: BSD
Classifier: Operating System :: POSIX :: Linux
Classifier: Programming Language :: Python
Classifier: Programming Language :: Python :: 3
Classifier: Programming Language :: Python :: 3.6
Classifier: Topic :: Database :: Database Engines/Servers
Classifier: Topic :: Other/Nonlisted Topic
Requires-Python: >=3.6
Requires-Dist: psycopg2-binary (>=2.8.3)
Requires-Dist: PyYAML (>=5.1.2)
Requires-Dist: Flask (>=1.1.2)
Requires-Dist: pg-chameleon (>=2.0)
